PythonMetaTrader5/__init__.py
pythonmetatrader5-2.3.2.dist-info/METADATA
pythonmetatrader5-2.3.2.dist-info/WHEEL
pythonmetatrader5-2.3.2.dist-info/top_level.txt
pythonmetatrader5-2.3.2.dist-info/RECORD
