Metadata-Version: 2.4
Name: PythonMetaTrader5
Version: 2.3.2
Summary: Connect MT5 with Python
Author-email: Wiktor Jelen <wiktorjn@gmail.com>
License: CC BY-NC 4.0
Project-URL: Homepage, https://github.com/Akinzou/MetaTrader5-Python
Project-URL: Bug Tracker, https://github.com/Akinzou/MetaTrader5-Python/issues
Classifier: Programming Language :: Python :: 3
Classifier: License :: OSI Approved :: MIT License
Classifier: Operating System :: OS Independent
Requires-Python: >=3.6
Requires-Dist: MetaTrader5
Requires-Dist: loguru
Requires-Dist: pyautogui
